{
  "state": "good",
  "episode_index": 10,
  "state_ordinal": 5,
  "start_time_wall": 1772914413.1284456,
  "end_time_wall": 1772914569.4626024,
  "wall_time_sec": 156.33415718600008,
  "lossy_calls": 5,
  "optimizer_steps": 4,
  "global_step_start": 559,
  "global_step_end": 639,
  "packets": 445915,
  "dropped": 0,
  "running_total_lossy_calls": 32,
  "running_total_optimizer_steps": 22,
  "running_total_packets": 2853856,
  "running_total_dropped": 20066,
  "running_total_time_sec": 1030.4343129940025,
  "lrb": 0.045,
  "lrg": 0.0,
  "steps": 0
}